.bumpversion.cfg
.editorconfig
.pre-commit-config.yaml
.readthedocs.yml
AUTHORS.rst
CHANGELOG.rst
CONTRIBUTING.rst
LICENSE
README.rst
noxfile.py
no_name/__init__.py
no_name/__main__.py
no_name/cli.py
no_name-0.0.0.dist-info/LICENSE
no_name-0.0.0.dist-info/METADATA
no_name-0.0.0.dist-info/WHEEL
no_name-0.0.0.dist-info/entry_points.txt
no_name-0.0.0.dist-info/RECORD
