Metadata-Version: 2.1
Name: no-name
Version: 0.0.0
Summary: An example package. Generated with cookiecutter-pylibrary.
Home-page: https://github.com/ugognw/python-no-name
License: BSD 2-Clause License
Keywords: Template
Author: Ugochukwu Nwosu
Requires-Python: >=3.10,<3.12
Classifier: Development Status :: 5 - Production/Stable
Classifier: Intended Audience :: Developers
Classifier: License :: OSI Approved :: BSD License
Classifier: License :: Other/Proprietary License
Classifier: Operating System :: Microsoft :: Windows
Classifier: Operating System :: POSIX
Classifier: Operating System :: Unix
Classifier: Programming Language :: Python
Classifier: Programming Language :: Python :: 3
Classifier: Programming Language :: Python :: 3.10
Classifier: Programming Language :: Python :: 3.11
Classifier: Programming Language :: Python :: 3 :: Only
Classifier: Programming Language :: Python :: Implementation :: CPython
Requires-Dist: click
Project-URL: Documentation, https://python-no-name.readthedocs.io/
Project-URL: Repository, https://github.com/ugognw/python-no-name
